simspec/__init__.py
simspec/__main__.py
simspec/simspec
simspec-1.11.0.dist-info/DESCRIPTION.rst
simspec-1.11.0.dist-info/METADATA
simspec-1.11.0.dist-info/RECORD
simspec-1.11.0.dist-info/WHEEL
simspec-1.11.0.dist-info/entry_points.txt
simspec-1.11.0.dist-info/metadata.json
simspec-1.11.0.dist-info/top_level.txt
