Metadata-Version: 2.0
Name: simspec
Version: 1.11.0
Summary: User interface for SimSpec. SIMplified SPECtrum reduction package for astronomy.
Home-page: http://astro.subhashbose.com/simspec
Author: Subhash Bose
Author-email: email@subhashbose.com
License: UNKNOWN
Platform: UNKNOWN
Classifier: Programming Language :: Python :: 2
Classifier: License :: Other/Proprietary License
Classifier: Operating System :: OS Independent
Requires-Dist: simspec-lib (>=2.4.4.0)
